letterguesser/__init__.py
letterguesser/__main__.py
letterguesser/assets/locales/en/LC_MESSAGES/messages.mo
letterguesser/assets/locales/en/LC_MESSAGES/messages.po
letterguesser/assets/locales/uk/LC_MESSAGES/messages.mo
letterguesser/assets/locales/uk/LC_MESSAGES/messages.po
letterguesser/assets/texts/en.txt
letterguesser/assets/texts/uk.txt
letterguesser/config.py
letterguesser/context.py
letterguesser/gui/__init__.py
letterguesser/gui/frames/__init__.py
letterguesser/gui/frames/AttemptsList.py
letterguesser/gui/frames/BaseFrame.py
letterguesser/gui/frames/BaseScrollFrame.py
letterguesser/gui/frames/BaseTable.py
letterguesser/gui/frames/HeaderFrame.py
letterguesser/gui/frames/InputFrame.py
letterguesser/gui/frames/LeftFrame.py
letterguesser/gui/frames/MainFrame.py
letterguesser/gui/frames/ProbabilityTable.py
letterguesser/gui/frames/RightFrame.py
letterguesser/gui/frames/StatusFrame.py
letterguesser/gui/widgets/__init__.py
letterguesser/gui/widgets/Button.py
letterguesser/gui/widgets/ButtonGroup.py
letterguesser/gui/widgets/Card.py
letterguesser/gui/widgets/CardGoup.py
letterguesser/gui/widgets/InputBlock.py
letterguesser/gui/widgets/List.py
letterguesser/gui/widgets/ListItem.py
letterguesser/gui/widgets/OptionMenu.py
letterguesser/gui/widgets/TextBlockSegment.py
letterguesser/logic/__init__.py
letterguesser/logic/Event.py
letterguesser/logic/ExperimentManager.py
letterguesser/logic/Localisation.py
letterguesser/logic/utils.py
letterguesser/py.typed
letterguesser/styles/__init__.py
letterguesser/styles/buttons.py
letterguesser/styles/colors.py
letterguesser/styles/font.py
letterguesser/styles/padding.py
letterguesser-1.0.0.dist-info/LICENSE
letterguesser-1.0.0.dist-info/METADATA
letterguesser-1.0.0.dist-info/WHEEL
letterguesser-1.0.0.dist-info/RECORD
